
 {
  "M_FAB2": "STRT",
  "FULL FORM": "STRUCTURE"
 },
 {
  "M_FAB2": "LP_KNIT",
  "FULL FORM": "LOOP KNIT"
 },
 {
  "M_FAB2": "ATSTPR",
  "FULL FORM": "AUTOSTRIPER"
 },
 {
  "M_FAB2": "FDSTPR",
  "FULL FORM": "FEEDER STRIPER"
 },
 {
  "M_FAB2": "JAQ",
  "FULL FORM": "JAQUARD"
 },
 {
  "M_FAB2": "TCOT",
  "FULL FORM": "TRICOT"
 },
 {
  "M_FAB2": "MESH",
  "FULL FORM": "MESH"
 },
 {
  "M_FAB2": "MINI_JAQ",
  "FULL FORM": "MINI JACQAURD "
 },
 {
  "M_FAB2": "TRF_JAQ",
  "FULL FORM": "TRANSFER JACQAURD "
 },
 {
  "M_FAB2": "CRUS",
  "FULL FORM": "SRUS"
 },
 {
  "M_FAB2": "FLT_BK",
  "FULL FORM": "FLAT BACK"
 },
 {
  "M_FAB2": "1X1",
  "FULL FORM": "1X1"
 },
 {
  "M_FAB2": "2X2",
  "FULL FORM": "2X2"
 },
 {
  "M_FAB2": "3X3",
  "FULL FORM": "3X3"
 },
 {
  "M_FAB2": "4X3",
  "FULL FORM": "4X3"
 },
 {
  "M_FAB2": "PNTL",
  "FULL FORM": "POINTAL"
 },
 {
  "M_FAB2": "HNYCMB",
  "FULL FORM": "HONEY COMB"
 },
 {
  "M_FAB2": "D_TUCK",
  "FULL FORM": "DOUBLE TUCK"
 },
 {
  "M_FAB2": "S_TUCK",
  "FULL FORM": "SINGLE TUCK"
 },
 {
  "M_FAB2": "CRNCL",
  "FULL FORM": "CRINCKLED"
 },
 {
  "M_FAB2": "DGNL",
  "FULL FORM": "DIAGONAL"
 },
 {
  "M_FAB2": "SHTNG",
  "FULL FORM": "SHEETING"
 },
 {
  "M_FAB2": "DMND",
  "FULL FORM": "DAIMOND"
 },
 {
  "M_FAB2": "2\/1",
  "FULL FORM": "2\/1"
 },
 {
  "M_FAB2": "3\/1",
  "FULL FORM": "3\/1"
 },
 {
  "M_FAB2": "1\/4",
  "FULL FORM": "1\/4"
 },
 {
  "M_FAB2": "4\/1",
  "FULL FORM": "4\/1"
 },
 {
  "M_FAB2": "2\/2",
  "FULL FORM": "2\/2"
 },
 {
  "M_FAB2": "HRNGBN",
  "FULL FORM": "HARRINGBONE"
 },
 {
  "M_FAB2": "BRKN_TWL",
  "FULL FORM": "BROKEN TWILL"
 },
 {
  "M_FAB2": "D_NDL",
  "FULL FORM": "DROP NEEDLE"
 },
 {
  "M_FAB2": "GRDL",
  "FULL FORM": "GRINDLE"
 },
 {
  "M_FAB2": "LRX",
  "FULL FORM": "LUREX"
 },
 {
  "M_FAB2": "CRP",
  "FULL FORM": "CREPE"
 },
 {
  "M_FAB2": "GIZA",
  "FULL FORM": "GIZA"
 },
 {
  "M_FAB2": "LYCL",
  "FULL FORM": "LYOCIL"
 },
 {
  "M_FAB2": "SLUB",
  "FULL FORM": "SLUB"
 },
 {
  "M_FAB2": "FOMA",
  "FULL FORM": "FOMA"
 },
 {
  "M_FAB2": "PLFL",
  "FULL FORM": "POLYFILL"
 },
 {
  "M_FAB2": "SHRP",
  "FULL FORM": "SHERPA"
 },
 {
  "M_FAB2": "NEPS",
  "FULL FORM": "NEPS"
 },
 {
  "M_FAB2": "MLNG",
  "FULL FORM": "MELANGE"
 },
 {
  "M_FAB2": "SYRO",
  "FULL FORM": "SYRO"
 },
 {
  "M_FAB2": "2_T_TR",
  "FULL FORM": "2 THREAD TERRY"
 },
 {
  "M_FAB2": "3_T_TR",
  "FULL FORM": "3 THREAD TERRY"
 },
 {
  "M_FAB2": "PLN",
  "FULL FORM": "PLAIN"
 },
 {
  "M_FAB2": "CHKN",
  "FULL FORM": "CHICKEN"
 },
 {
  "M_FAB2": "BRSHNG",
  "FULL FORM": "BRUSHING"
 },
 {
  "M_FAB2": "W_RSNG",
  "FULL FORM": "W RAISING"
 },
 {
  "M_FAB2": "IND",
  "FULL FORM": "INDIGO"
 }
